adminui/__init__.py
adminui/actions.py
adminui/app.py
adminui/chart.py
adminui/element.py
adminui/feedback.py
adminui/form.py
adminui/layout.py
adminui/page.py
adminui/table.py
adminui/static/asset-manifest.json
adminui/static/favicon.png
adminui/static/index.html
adminui/static/layouts__BasicLayout.1d77ce3c.async.js
adminui/static/layouts__BasicLayout.ae762f70.chunk.css
adminui/static/layouts__UserLayout.405c888c.chunk.css
adminui/static/layouts__UserLayout.a867a7d8.async.js
adminui/static/menu.json
adminui/static/p__404.a2742951.async.js
adminui/static/p__index.0b4b102d.chunk.css
adminui/static/p__index.3585e795.async.js
adminui/static/p__user__login.fb672c98.async.js
adminui/static/p__user__login.fc8aa21b.chunk.css
adminui/static/umi.15c5cff9.js
adminui/static/umi.c879072d.css
adminui/static/vendors.42feb457.chunk.css
adminui/static/vendors.883c7e19.async.js
adminui/static/icons/icon-128x128.png
adminui/static/icons/icon-192x192.png
adminui/static/icons/icon-512x512.png
example_shared_app/__init__.py
example_shared_app/detail.py
example_shared_app/main.py
tests/__init__.py
tests/test_app.py
tests/test_form.py
adminui2-1.5.6.dist-info/LICENSE
adminui2-1.5.6.dist-info/METADATA
adminui2-1.5.6.dist-info/WHEEL
adminui2-1.5.6.dist-info/top_level.txt
adminui2-1.5.6.dist-info/RECORD
