Metadata-Version: 2.1
Name: adminui2
Version: 1.5.6
Summary: Write professional web interface with Python
Home-page: https://github.com/XemonDev/python-adminui
Author: Yashar (XemonDev)
Author-email: XemonDev@gmail.com
Classifier: Programming Language :: Python :: 3
Classifier: License :: OSI Approved :: MIT License
Classifier: Operating System :: OS Independent
Requires-Python: >=3.6
License-File: LICENSE
Requires-Dist: aioflask==0.4.0
Requires-Dist: asgiref==3.5.2
Requires-Dist: click==8.1.3
Requires-Dist: flask==3.1.0
Requires-Dist: greenlet==3.1.1
Requires-Dist: greenletio==0.9.0
Requires-Dist: gunicorn==20.1.0
Requires-Dist: h11==0.13.0
Requires-Dist: importlib-metadata==4.12.0
Requires-Dist: itsdangerous==2.2.0
Requires-Dist: Jinja2==3.1.2
Requires-Dist: MarkupSafe==2.1.1
Requires-Dist: PyJWT==2.3.0
Requires-Dist: python-multipart==0.0.5
Requires-Dist: six==1.16.0
Requires-Dist: uvicorn==0.18.0
Requires-Dist: Werkzeug==3.1.3
Requires-Dist: zipp==3.8.1
